changelog/.gitempty
dkist_processing_common/__init__.py
dkist_processing_common/config.py
dkist_processing_common/manual.py
dkist_processing_common/_util/__init__.py
dkist_processing_common/_util/constants.py
dkist_processing_common/_util/graphql.py
dkist_processing_common/_util/scratch.py
dkist_processing_common/_util/tags.py
dkist_processing_common/codecs/__init__.py
dkist_processing_common/codecs/array.py
dkist_processing_common/codecs/asdf.py
dkist_processing_common/codecs/basemodel.py
dkist_processing_common/codecs/bytes.py
dkist_processing_common/codecs/fits.py
dkist_processing_common/codecs/iobase.py
dkist_processing_common/codecs/json.py
dkist_processing_common/codecs/path.py
dkist_processing_common/codecs/quality.py
dkist_processing_common/codecs/str.py
dkist_processing_common/fonts/Lato-Regular.ttf
dkist_processing_common/fonts/__init__.py
dkist_processing_common/models/__init__.py
dkist_processing_common/models/constants.py
dkist_processing_common/models/dkist_location.py
dkist_processing_common/models/extras.py
dkist_processing_common/models/fits_access.py
dkist_processing_common/models/flower_pot.py
dkist_processing_common/models/fried_parameter.py
dkist_processing_common/models/graphql.py
dkist_processing_common/models/input_dataset.py
dkist_processing_common/models/message.py
dkist_processing_common/models/message_queue_binding.py
dkist_processing_common/models/metric_code.py
dkist_processing_common/models/parameters.py
dkist_processing_common/models/quality.py
dkist_processing_common/models/tags.py
dkist_processing_common/models/task_name.py
dkist_processing_common/models/telemetry.py
dkist_processing_common/models/wavelength.py
dkist_processing_common/parsers/__init__.py
dkist_processing_common/parsers/average_bud.py
dkist_processing_common/parsers/cs_step.py
dkist_processing_common/parsers/dsps_repeat.py
dkist_processing_common/parsers/experiment_id_bud.py
dkist_processing_common/parsers/id_bud.py
dkist_processing_common/parsers/l0_fits_access.py
dkist_processing_common-12.2.0.dist-info/METADATA
dkist_processing_common-12.2.0.dist-info/WHEEL
dkist_processing_common-12.2.0.dist-info/top_level.txt
dkist_processing_common-12.2.0.dist-info/RECORD
