Metadata-Version: 2.4
Name: dkist-processing-common
Version: 12.2.0
Summary: Common task classes used by the DKIST science data processing pipelines
Author-email: NSO / AURA <dkistdc@nso.edu>
License: BSD-3-Clause
Project-URL: Homepage, https://nso.edu/dkist/data-center/
Project-URL: Repository, https://bitbucket.org/dkistdc/dkist-processing-common/
Project-URL: Documentation, https://docs.dkist.nso.edu/projects/common
Project-URL: Help, https://nso.atlassian.net/servicedesk/customer/portal/5
Classifier: Programming Language :: Python
Classifier: Programming Language :: Python :: 3
Classifier: Programming Language :: Python :: 3.13
Requires-Python: >=3.13
Requires-Dist: asdf<4.0.0,>=3.5.0
Requires-Dist: astropy>=7.0.0
Requires-Dist: dkist-fits-specifications<5.0,>=4.0.0
Requires-Dist: dkist-header-validator<6.0,>=5.3.0
Requires-Dist: dkist-processing-core==7.0.1
Requires-Dist: dkist-processing-pac<4.0,>=3.1
Requires-Dist: dkist-service-configuration<5.0,>=4.2.0
Requires-Dist: dkist-spectral-lines<4.0,>=3.0.0
Requires-Dist: solar-wavelength-calibration<3.0,>=2.0.0
Requires-Dist: globus-sdk<5.0.0,>=4.0.0
Requires-Dist: gqlclient[pydantic]==1.2.3
Requires-Dist: sqids==0.5.1
Requires-Dist: matplotlib>=3.4
Requires-Dist: moviepy>=2.0.0
Requires-Dist: numpy>=1.26.4
Requires-Dist: object-clerk==1.0.0
Requires-Dist: pandas>=1.4.2
Requires-Dist: pillow>=10.2.0
Requires-Dist: pydantic>=2.7.2
Requires-Dist: redis==6.4.0
Requires-Dist: requests>=2.23
Requires-Dist: scipy>=1.15.1
Requires-Dist: sunpy>=3.0.0
Requires-Dist: talus==1.3.4
Provides-Extra: test
Requires-Dist: pytest; extra == "test"
Requires-Dist: pytest-xdist; extra == "test"
Requires-Dist: pytest-cov; extra == "test"
Requires-Dist: pytest-mock; extra == "test"
Requires-Dist: hypothesis; extra == "test"
Requires-Dist: towncrier; extra == "test"
Requires-Dist: dkist-data-simulator>=5.2.6; extra == "test"
Requires-Dist: dkist-processing-common[inventory]; extra == "test"
Requires-Dist: dkist-processing-common[asdf]; extra == "test"
Requires-Dist: dkist-processing-common[quality]; extra == "test"
Provides-Extra: docs
Requires-Dist: sphinx; extra == "docs"
Requires-Dist: sphinx-astropy; extra == "docs"
Requires-Dist: sphinx-changelog; extra == "docs"
Requires-Dist: sphinx-autoapi!=3.1.0; extra == "docs"
Requires-Dist: pytest; extra == "docs"
Requires-Dist: towncrier<22.12.0; extra == "docs"
Requires-Dist: dkist-sphinx-theme; extra == "docs"
Provides-Extra: inventory
Requires-Dist: dkist-inventory<2.0,>=1.11.2; extra == "inventory"
Provides-Extra: asdf
Requires-Dist: dkist-inventory[asdf]<2.0,>=1.11.2; extra == "asdf"
Provides-Extra: quality
Requires-Dist: dkist-quality<3.0,>=2.0.0; extra == "quality"
